{"derivation": "from G1097 (\u03b3\u03bd\u1ff6\u03c3\u03b9\u03c2);", "kjv_def": "knowledge, science", "lemma": "\u03b3\u03bd\u1ff6\u03c3\u03b9\u03c2", "frequency": 33, "strongs_def": " knowing (the act), i.e. (by implication) knowledge", "outline": "<ol><li> knowledge signifies in general intelligence, understanding<ol><li> the general knowledge of Christian religion</li><li> the deeper more perfect and enlarged knowledge of this religion, such as belongs to the more advanced</li><li> esp. of things lawful and unlawful for Christians</li><li> moral wisdom, such as is seen in right living</li></ol></li></ol>"}