{"derivation": "from G1176 (\u0394\u03b5\u03ba\u03ac\u03c0\u03bf\u03bb\u03b9\u03c2) and G4172 (\u0394\u03b5\u03ba\u03ac\u03c0\u03bf\u03bb\u03b9\u03c2);", "kjv_def": "Decapolis", "lemma": "\u0394\u03b5\u03ba\u03ac\u03c0\u03bf\u03bb\u03b9\u03c2", "frequency": 3, "strongs_def": " the ten-city region; the Decapolis, a district in Syria", "outline": "<span class=\"literal-meaning\">Decapolis = &quot;ten cities&quot;</span><ol><li> a track of land so called from the ten cities that were in it<ol><li> according to Pliny, these cities were: Damascus, Opoton, Philadelphia, Raphana, Scythopolis, Gadara, Hippondion, Pella, Galasa, and Canatha (Gill)</li></ol></li></ol>"}