{"derivation": "from a derivative of G1492 (\u1f31\u03c3\u03c4\u03bf\u03c1\u03ad\u03c9);", "kjv_def": "see", "lemma": "\u1f31\u03c3\u03c4\u03bf\u03c1\u03ad\u03c9", "frequency": 1, "strongs_def": " to be knowing (learned), i.e. (by implication) to visit for information (interview)", "outline": "<ol><li> to enquire into, examine, investigate</li><li> to find out, learn, by enquiry</li><li> to gain knowledge of by visiting<ol><li> of some distinguished person, to become personally acquainted with, know face to face</li></ol></li></ol>"}