{"derivation": "of Latin origin;", "kjv_def": "tribute", "lemma": "\u03ba\u1fc6\u03bd\u03c3\u03bf\u03c2", "frequency": 4, "strongs_def": " properly, an enrollment (\"census\"), i.e. (by implication) a tax", "outline": "<ol><li> census (among the Romans, denoting a register and valuation of property in accordance with which taxes were paid), in the NT the tax or tribute levied on individuals and to be paid yearly. (our capitation or poll tax)</li><li> the coin with which the tax is paid, tribute money</li></ol>"}