{"derivation": "from G3011 (\u03bb\u03b5\u03b9\u03c4\u03bf\u03c5\u03c1\u03b3\u03ad\u03c9);", "kjv_def": "minister", "lemma": "\u03bb\u03b5\u03b9\u03c4\u03bf\u03c5\u03c1\u03b3\u03ad\u03c9", "frequency": 3, "strongs_def": " to be a public servant, i.e. (by analogy) to perform religious or charitable functions (worship, obey, relieve)", "outline": "<ol><li> to serve the state at one's own cost<ol><li> to assume an office which must be administered at one's own expense</li><li> to discharge a public office at one's own cost</li><li> to render public service to the state</li></ol><li> to do a service, perform a work<ol><li> of priests and Levites who were busied with the sacred rites in the tabernacle or the temple</li><li> of Christians serving Christ, whether by prayer, or by instructing others concerning the way of salvation, or in some other way</li><li> of those who aid others with their resources, and relieve their poverty</li></ol></li></ol>"}