{"derivation": "a primary verb;", "kjv_def": "break (up), destroy, dissolve, (un-)loose, melt, put off", "lemma": "\u03bb\u03cd\u03c9", "frequency": 43, "strongs_def": " to \"loosen\" (literally or figuratively)", "outline": "<ol><li> to loose any person (or thing) tied or fastened<ol><li> bandages of the feet, the shoes,</li><li> of a husband and wife joined together by the bond of matrimony</li><li> of a single man, whether he has already had a wife or has not yet married</li></ol><li> to loose one bound, i.e. to unbind, release from bonds, set free<ol><li> of one bound up (swathed in bandages)</li><li> bound with chains (a prisoner), discharge from prison, let go</li></ol><li> to loosen, undo, dissolve, anything bound, tied, or compacted together<ol><li> an assembly, i.e. to dismiss, break up</li><li> laws, as having a binding force, are likened to bonds</li><li> to annul, subvert</li><li> to do away with, to deprive of authority, whether by precept or act</li><li> to declare unlawful</li><li> to loose what is compacted or built together, to break up, demolish, destroy</li><li> to dissolve something coherent into parts, to destroy</li><li> metaph., to overthrow, to do away with</li></ol></li></ol>"}