{"derivation": "from G3110 (\u039c\u03b1\u03ba\u03b5\u03b4\u03bf\u03bd\u03af\u03b1);", "kjv_def": "Macedonia", "lemma": "\u039c\u03b1\u03ba\u03b5\u03b4\u03bf\u03bd\u03af\u03b1", "frequency": 18, "strongs_def": " Macedonia, a region of Greece", "outline": "<span class=\"literal-meaning\">Macedonia = &quot;extended land&quot;</span><ol><li> a country bounded on the south by Thessaly and Epirus, on the east by Thrace and the Aegean Sea, on the west by Illyria, and on the North by Dardania and Moesia</li></ol>"}