{"derivation": "from G3326 (\u03bc\u03b5\u03c4\u03b1\u03bd\u03bf\u03ad\u03c9) and G3539 (\u03bc\u03b5\u03c4\u03b1\u03bd\u03bf\u03ad\u03c9);", "kjv_def": "repent", "lemma": "\u03bc\u03b5\u03c4\u03b1\u03bd\u03bf\u03ad\u03c9", "frequency": 33, "strongs_def": " to think differently or afterwards, i.e. reconsider (morally, feel compunction)", "outline": "<ol><li> to change one's mind, i.e. to repent</li><li> to change one's mind for better, heartily to amend with abhorrence of one's past sins</li></ol>"}