{"derivation": "apparently from the base of G3796 (\u1f40\u03c0\u03ce\u03c1\u03b1) and G5610 (\u1f40\u03c0\u03ce\u03c1\u03b1);", "kjv_def": "fruit", "lemma": "\u1f40\u03c0\u03ce\u03c1\u03b1", "frequency": 1, "strongs_def": " properly, even-tide of the (summer) season (dog-days), i.e. (by implication) ripe fruit", "outline": "<ol><li> the season which succeeds summer, from the rising of Sirius to that of Arcturus, i.e. from late summer, early autumn, our dog days</li><li> ripe fruits (of trees)</li></ol>"}