{"derivation": "from G303 (\u1f00\u03bd\u03b1\u03c4\u03ad\u03bb\u03bb\u03c9) and the base of G5056 (\u1f00\u03bd\u03b1\u03c4\u03ad\u03bb\u03bb\u03c9);", "kjv_def": "(a-, make to) rise, at the rising of, spring (up), be up", "lemma": "\u1f00\u03bd\u03b1\u03c4\u03ad\u03bb\u03bb\u03c9", "frequency": 9, "strongs_def": " to (cause to) arise", "outline": "<ol><li> rise<ol><li> to cause to rise<ol><li> of the earth bring forth plants</li></ol><li> to rise, arise, to rise from, be descended from<ol><li> of sun moon and stars)</li></ol></li></ol></li></ol>"}