{"derivation": "from G4862 (\u03c3\u03c5\u03b3\u03ba\u03b1\u03ba\u03bf\u03c5\u03c7\u03ad\u03c9) and G2558 (\u03c3\u03c5\u03b3\u03ba\u03b1\u03ba\u03bf\u03c5\u03c7\u03ad\u03c9);", "kjv_def": "suffer affliction with", "lemma": "\u03c3\u03c5\u03b3\u03ba\u03b1\u03ba\u03bf\u03c5\u03c7\u03ad\u03c9", "frequency": 1, "strongs_def": " to maltreat in company with, i.e. (passively) endure persecution together", "outline": "<ol><li> to treat ill with another</li><li> to be ill treated in company with, share persecutions or come into a fellowship of ills</li></ol>"}