{"derivation": "from G473 (\u1f00\u03bd\u03c4\u03b9\u03bb\u03ad\u03b3\u03c9) and G3004 (\u1f00\u03bd\u03c4\u03b9\u03bb\u03ad\u03b3\u03c9);", "kjv_def": "answer again, contradict, deny, gainsay(-er), speak against", "lemma": "\u1f00\u03bd\u03c4\u03b9\u03bb\u03ad\u03b3\u03c9", "frequency": 10, "strongs_def": " to dispute, refuse", "outline": "<ol><li> to speak against, gainsay, contradict</li><li> to oppose one's self to one, decline to obey him, declare one's self against him, refuse to have anything to do with him</li></ol>"}