{"derivation": "feminine of a compound of G4948 (\u03a3\u03c5\u03c1\u03bf\u03c6\u03bf\u03af\u03bd\u03b9\u03c3\u03c3\u03b1) and the same as G5403 (\u03a3\u03c5\u03c1\u03bf\u03c6\u03bf\u03af\u03bd\u03b9\u03c3\u03c3\u03b1);", "kjv_def": "Syrophenician", "lemma": "\u03a3\u03c5\u03c1\u03bf\u03c6\u03bf\u03af\u03bd\u03b9\u03c3\u03c3\u03b1", "frequency": 1, "strongs_def": " a Syro-ph\u0153nician woman, i.e. a female native of Ph\u0153nicia in Syria", "outline": "<span class=\"literal-meaning\">Syrophenician = \"exalted palm\"</span><ol><li> the name of a mixed nation, half Phoenicians and half Syrians</li></ol>"}