{"derivation": "probably strengthened from G5420 (\u03c3\u03c6\u03c1\u03b1\u03b3\u03af\u03c2);", "kjv_def": "seal", "lemma": "\u03c3\u03c6\u03c1\u03b1\u03b3\u03af\u03c2", "frequency": 17, "strongs_def": " a signet (as fencing in or protecting from misappropriation); by implication, the stamp impressed (as a mark of privacy, or genuineness), literally or figuratively", "outline": "<ol><li> a seal<ol><li> the seal placed upon books</li><li> a signet ring</li><li> the inscription or impression made by a seal<ol><li> of the name of God and Christ stamped upon their foreheads</li></ol><li> that by which anything is confirmed, proved, authenticated, as by a seal (a token or proof)</li></ol></li></ol>"}