{"derivation": "from G5062 (\u03c4\u03b5\u03c3\u03c3\u03b1\u03c1\u03b1\u03ba\u03bf\u03bd\u03c4\u03b1\u03b5\u03c4\u03ae\u03c2) and G2094 (\u03c4\u03b5\u03c3\u03c3\u03b1\u03c1\u03b1\u03ba\u03bf\u03bd\u03c4\u03b1\u03b5\u03c4\u03ae\u03c2);", "kjv_def": "(+ full, of) forty years (old)", "lemma": "\u03c4\u03b5\u03c3\u03c3\u03b1\u03c1\u03b1\u03ba\u03bf\u03bd\u03c4\u03b1\u03b5\u03c4\u03ae\u03c2", "frequency": 2, "strongs_def": " of forty years of age", "outline": "<ol><li> of forty years, forty years old</li></ol>"}