{"derivation": "from G575 (\u1f00\u03c0\u03bf\u03b2\u03bb\u03ad\u03c0\u03c9) and G991 (\u1f00\u03c0\u03bf\u03b2\u03bb\u03ad\u03c0\u03c9);", "kjv_def": "have respect", "lemma": "\u1f00\u03c0\u03bf\u03b2\u03bb\u03ad\u03c0\u03c9", "frequency": 1, "strongs_def": " to look away from everything else, i.e. (figuratively) intently regard", "outline": "<ol><li> to turn the eyes away from other things and fix them on some one thing<ol><li> to look at attentively</li></ol><li> to look with steadfast mental gaze</li></ol>"}