{"derivation": "a primitive root;", "pron": "baw-naw'", "outline": "<ol><li> to build, rebuild, establish, cause to continue<ol><li> (Qal)<ol><li> to build, rebuild</li><li> to build a house (ie, establish a family)</li></ol><li> (Niphal)<ol><li> to be built</li><li> to be rebuilt</li><li> established (of restored exiles) (fig.)</li><li> established (made permanent)</li><li> to be built up (of childless wife becoming the mother of a family through the children of a concubine)</li></ol></li></ol></li></ol>", "kjv_def": "(begin to) build(-er), obtain children, make, repair, set (up), [idiom] surely.", "lemma": "\u05d1\u05bc\u05b8\u05e0\u05b8\u05d4", "frequency": 375, "strongs_def": "to build (literally and figuratively)", "xlit": "b\u00e2n\u00e2h"}