{"derivation": "a primitive root; to clip off; specifically (as denominative from H1210 (\u05d1\u05bc\u05b8\u05e6\u05b4\u05d9\u05e8))", "pron": "baw-tsar'", "outline": "<ol><li> to gather, restrain, fence, fortify, make inaccessible, enclose<ol><li> (Qal)<ol><li> to cut off</li><li> fortified, cut off, made inaccessible (pass participle)</li><li> secrets, mysteries, inaccessible things (subst)</li></ol><li> (Niphal) to be withheld</li><li> (Piel) to fortify</li></ol></li></ol>", "kjv_def": "cut off, (de-) fenced, fortify, (grape) gather(-er), mighty things, restrain, strong, wall (up), withhold.", "lemma": "\u05d1\u05bc\u05b8\u05e6\u05b7\u05e8", "frequency": 38, "strongs_def": "to gather grapes; also to be isolated (i.e. inaccessible by height or fortification)", "xlit": "b\u00e2tsar"}