{"derivation": "or \u05d4\u05b2\u05d3\u05b9\u05e8\u05b8\u05dd; probably of foreign derivation;", "pron": "had-o-rawm'", "outline": "<span class=\"literal-meaning\">Hadoram = &quot;noble honour&quot;</span><ol><li> the 5th son of Joktan</li><li> a son of Tou, king of Hamath, was his father's ambassador to congratulate David on his victory over Hadarezer, king of Zobah</li><li> the intendant of taxes under David, Solomon, and Rehoboam; called also 'Adoniram' and 'Adoram'</li></ol>", "kjv_def": "Hadoram.", "lemma": "\u05d4\u05b2\u05d3\u05d5\u05b9\u05e8\u05b8\u05dd", "frequency": 4, "strongs_def": "Hadoram, a son of Joktan, and the tribe descended from him", "xlit": "H\u0103d\u00f4wr\u00e2m"}