{"derivation": "from H2388 (\u05d7\u05b8\u05d6\u05b7\u05e7) and H410 (\u05d0\u05b5\u05dc); God will strengthen;", "pron": "yekh-ez-kale'", "outline": "<span class=\"literal-meaning\">Ezekiel or Jehezekel = &quot;God strengthens&quot;</span><ol><li> son of Buzi and a priest and prophet; author of the book by his name; taken captive with Jehoiachin and exiled in Babylon where he prophesied for the next 22 years</li><li> a priest in charge of the 20th course in the time of David</li></ol>", "kjv_def": "Ezekiel, Jehezekel.", "lemma": "\u05d9\u05b0\u05d7\u05b6\u05d6\u05b0\u05e7\u05b5\u05d0\u05dc", "frequency": 3, "strongs_def": "Jechezkel, the name of two Israelites", "xlit": "Y\u1d49chezq\u00ea\u02bcl"}