{"derivation": "shortened from H352 (\u05d0\u05b7\u05d9\u05b4\u05dc);", "pron": "ale", "outline": "<ol><li> god, god-like one, mighty one<ol><li> mighty men, men of rank, mighty heroes</li><li> angels</li><li> god, false god, (demons, imaginations)</li><li> God, the one true God, Jehovah</li></ol><li> mighty things in nature</li><li> strength, power</li></ol>", "kjv_def": "God (god), [idiom] goodly, [idiom] great, idol, might(-y one), power, strong. Compare names in '-el.'", "lemma": "\u05d0\u05b5\u05dc", "frequency": 248, "strongs_def": "strength; as adjective, mighty; especially the Almighty (but used also of any deity)", "xlit": "\u02bc\u00eal"}