{"derivation": "feminine of H4474 (\u05de\u05b4\u05de\u05b0\u05e9\u05c1\u05b8\u05dc);", "pron": "mem-shaw-law'", "outline": "<ol><li> rule, dominion, realm<ol><li> rule, dominion, realm, domain</li><li> rule</li><li> rule, dominion (of God)</li></ol></li></ol>", "kjv_def": "dominion, government, power, to rule.", "lemma": "\u05de\u05b6\u05de\u05b0\u05e9\u05c1\u05b8\u05dc\u05b8\u05d4", "frequency": 14, "strongs_def": "rule; also (concretely in plural) a realm or a ruler", "xlit": "memsh\u00e2l\u00e2h"}