{"derivation": "or \u05d0\u05b2\u05de\u05b4\u05d9\u05e0\u05d5\u05b9\u05df; from H539 (\u05d0\u05b8\u05de\u05b7\u05df); faithful;", "pron": "am-nohn'", "outline": "<span class=\"literal-meaning\">Amnon = &quot;faithful&quot;</span><ol><li> oldest son of David, rapist of Tamar, slain by Absalom</li><li> a son of Shimon (of Caleb's clan)</li></ol>", "kjv_def": "Amnon.", "lemma": "\u05d0\u05b7\u05de\u05b0\u05e0\u05d5\u05b9\u05df", "frequency": 28, "strongs_def": "Amnon (or Aminon), a son of David", "xlit": "\u02bcAmn\u00f4wn"}