{"derivation": "patronymically from H5816 (\u05e2\u05bb\u05d6\u05bc\u05b4\u05d9\u05d0\u05b5\u05dc);", "pron": "oz-zee-ay-lee'", "outline": "<span class=\"literal-meaning\">Uzzielites = see Uzziel &quot;my strength is God&quot;</span><ol><li> descendants of Uzziel</li></ol>", "kjv_def": "Uzzielites.", "lemma": "\u05e2\u05c7\u05d6\u05bc\u05b4\u05d9\u05d0\u05b5\u05dc\u05b4\u05d9", "frequency": 2, "strongs_def": "an Uzzielite (collectively) or descendants of Uzziel", "xlit": "\u02bbOzz\u00eey\u02bc\u00eal\u00eey"}