{"derivation": "from H6006 (\u05e2\u05b8\u05de\u05b7\u05e1); burdensome;", "pron": "aw-moce'", "outline": "<span class=\"literal-meaning\">Amos = &quot;burden&quot;</span><ol><li> a prophet of the Lord who prophesied in the northern kingdom; native of Tekoa in Judah near Bethlehem and a shepherd by trade; author of the prophetic book by his name</li></ol>", "kjv_def": "Amos.", "lemma": "\u05e2\u05b8\u05de\u05d5\u05b9\u05e1", "frequency": 7, "strongs_def": "Amos, an Israelite prophet", "xlit": "\u02bb\u00c2m\u00f4w\u00e7"}