{"derivation": "a primitive root;", "pron": "tsaw-vaw'", "outline": "<ol><li> to command, charge, give orders, lay charge, give charge to, order<ol><li> (Piel)<ol><li> to lay charge upon</li><li> to give charge to, give command to</li><li> to give charge unto</li><li> to give charge over, appoint</li><li> to give charge, command</li><li> to charge, command</li><li> to charge, commission</li><li> to command, appoint, ordain (of divine act)</li></ol><li> (Pual) to be commanded</li></ol></li></ol>", "kjv_def": "appoint, (for-) bid, (give a) charge, (give a, give in, send with) command(-er, -ment), send a messenger, put, (set) in order.", "lemma": "\u05e6\u05b8\u05d5\u05b8\u05d4", "frequency": 493, "strongs_def": "(intensively) to constitute, enjoin", "xlit": "ts\u00e2v\u00e2h"}