{"derivation": "or (feminine) \u05e6\u05b7\u05dc\u05b0\u05e2\u05b8\u05d4; from H6760 (\u05e6\u05b8\u05dc\u05b7\u05e2);", "pron": "tsay-law'", "outline": "<ol><li> side, rib, beam<ol><li> rib (of man)</li><li> rib (of hill, ridge, etc)</li><li> side-chambers or cells (of temple structure)</li><li> rib, plank, board (of cedar or fir)</li><li> leaves (of door)</li><li> side (of ark)</li></ol></li></ol>", "kjv_def": "beam, board, chamber, corner, leaf, plank, rib, side (chamber).", "lemma": "\u05e6\u05b5\u05dc\u05b8\u05e2", "frequency": 41, "strongs_def": "a rib (as curved), literally (of the body) or figuratively (of a door, i.e. leaf); hence, a side, literally (of a person) or figuratively (of an object or the sky, i.e. quarter); architecturally, a (especially floor or ceiling) timber or plank (single or collective, i.e. a flooring)", "xlit": "ts\u00eal\u00e2\u02bb"}