{"derivation": "or \u05e8\u05b8\u05d0\u05de\u05b9\u05eaxlit R\u00e2m\u00f4th corrected to R\u00e2\u02bcm\u00f4th; plural of H7215 (\u05e8\u05b8\u05d0\u05de\u05b8\u05d4); heights;", "pron": "raw-moth'", "outline": "<span class=\"literal-meaning\">Ramoth = &quot;heights&quot;</span><ol><li> a place in Gilead; site dubious</li><li> a Levitical city in Issachar</li></ol>", "kjv_def": "Ramoth.", "lemma": "\u05e8\u05b8\u05d0\u05de\u05d5\u05b9\u05ea", "frequency": 4, "strongs_def": "Ramoth, the name of two places in Palestine", "xlit": "R\u00e2\u02bcm\u00f4wth"}