{"derivation": "dual of an unused singular \u05e9\u05c1\u05b8\u05de\u05b6\u05d4; from an unused root meaning to be lofty;", "pron": "shaw-mah'-yim", "outline": "<ol><li> heaven, heavens, sky<ol><li> visible heavens, sky<ol><li> as abode of the stars</li><li> as the visible universe, the sky, atmosphere, etc</li></ol><li> Heaven (as the abode of God)</li></ol></li></ol>", "kjv_def": "air, [idiom] astrologer, heaven(-s).", "lemma": "\u05e9\u05c1\u05b8\u05de\u05b7\u05d9\u05b4\u05dd", "frequency": 421, "strongs_def": "the sky (as aloft; the dual perhaps alluding to the visible arch in which the clouds move, as well as to the higher ether where the celestial bodies revolve)", "xlit": "sh\u00e2mayim"}