{"derivation": "a primitive relative pronoun (of every gender and number);", "pron": "ash-er'", "outline": "<ol><li> (relative part.)<ol><li> which, who</li><li> that which</li></ol><li> (conj)<ol><li> that (in obj clause)</li><li> when</li><li> since</li><li> as</li><li> conditional if</li></ol></li></ol>", "kjv_def": "[idiom] after, [idiom] alike, as (soon as), because, [idiom] every, for, [phrase] forasmuch, [phrase] from whence, [phrase] how(-soever), [idiom] if, (so) that ((thing) which, wherein), [idiom] though, [phrase] until, [phrase] whatsoever, when, where ([phrase] -as, -in, -of, -on, -soever, -with), which, whilst, [phrase] whither(-soever), who(-m, -soever, -se). As it is indeclinable, it is often accompanied by the personal pronoun expletively, used to show the connection.", "lemma": "\u05d0\u05b2\u05e9\u05c1\u05b6\u05e8", "frequency": 5502, "strongs_def": "who, which, what, that; also (as an adverb and a conjunction) when, where, how, because, in order that, etc.", "xlit": "\u02bc\u0103sher"}