{"derivation": "a primitive root;", "pron": "taw-fas'", "outline": "<ol><li> to catch, handle, lay hold, take hold of, seize, wield<ol><li> (Qal)<ol><li> to lay hold of, seize, arrest, catch</li><li> to grasp (in order to) wield, wield, use skilfully</li></ol><li> (Niphal) to be seized, be arrested, be caught, be taken, captured</li><li> (Piel) to catch, grasp (with the hands)</li></ol></li></ol>", "kjv_def": "catch, handle, (lay, take) hold (on, over), stop, [idiom] surely, surprise, take.", "lemma": "\u05ea\u05bc\u05b8\u05e4\u05b7\u05e9\u05c2", "frequency": 65, "strongs_def": "to manipulate, i.e. seize; chiefly to capture, wield, specifically, to overlay; figuratively, to use unwarrantably", "xlit": "t\u00e2phas"}