{"derivation": "from H1101 (\u05d1\u05bc\u05b8\u05dc\u05b7\u05dc); confusion;", "pron": "baw-bel'", "outline": "<span class=\"literal-meaning\">Babel or Babylon = &quot;confusion (by mixing)&quot;</span><ol><li> Babel or Babylon, the ancient site and/or capital of Babylonia (modern Hillah) situated on the Euphrates</li></ol>", "kjv_def": "Babel, Babylon.", "lemma": "\u05d1\u05bc\u05b8\u05d1\u05b6\u05dc", "frequency": 262, "strongs_def": "Babel (i.e. Babylon), including Babylonia and the Babylonian empire", "xlit": "B\u00e2bel"}